security_controls_mcp/__init__.py
security_controls_mcp/__main__.py
security_controls_mcp/cli.py
security_controls_mcp/config.py
security_controls_mcp/data_loader.py
security_controls_mcp/http_server.py
security_controls_mcp/legal_notice.py
security_controls_mcp/providers.py
security_controls_mcp/registry.py
security_controls_mcp/server.py
security_controls_mcp/data/framework-to-scf.json
security_controls_mcp/data/scf-controls.json
security_controls_mcp/extractors/__init__.py
security_controls_mcp/extractors/pdf_extractor.py
security_controls_mcp-0.3.5.dist-info/licenses/LICENSE
security_controls_mcp-0.3.5.dist-info/licenses/LICENSE-DATA.md
security_controls_mcp-0.3.5.dist-info/METADATA
security_controls_mcp-0.3.5.dist-info/WHEEL
security_controls_mcp-0.3.5.dist-info/entry_points.txt
security_controls_mcp-0.3.5.dist-info/top_level.txt
security_controls_mcp-0.3.5.dist-info/RECORD
