Metadata-Version: 2.4
Name: security-controls-mcp
Version: 0.3.5
Summary: MCP server for querying security framework controls (SCF) - map between ISO 27001, NIST CSF, DORA, PCI DSS, and more
Author-email: Ansvar Systems <hello@ansvar.eu>
License-Expression: Apache-2.0
Project-URL: Homepage, https://github.com/Ansvar-Systems/security-controls-mcp
Project-URL: Repository, https://github.com/Ansvar-Systems/security-controls-mcp
Project-URL: Issues, https://github.com/Ansvar-Systems/security-controls-mcp/issues
Keywords: mcp,security,compliance,iso27001,nist,dora,pci-dss
Classifier: Development Status :: 4 - Beta
Classifier: Intended Audience :: Developers
Classifier: Programming Language :: Python :: 3
Classifier: Programming Language :: Python :: 3.10
Classifier: Programming Language :: Python :: 3.11
Classifier: Programming Language :: Python :: 3.12
Requires-Python: >=3.10
License-File: LICENSE
License-File: LICENSE-DATA.md
Requires-Dist: mcp>=0.9.0
Provides-Extra: dev
Requires-Dist: pytest>=7.0.0; extra == "dev"
Requires-Dist: pytest-asyncio>=0.21.0; extra == "dev"
Requires-Dist: black>=23.0.0; extra == "dev"
Requires-Dist: ruff>=0.1.0; extra == "dev"
Requires-Dist: pre-commit>=3.0.0; extra == "dev"
Provides-Extra: import-tools
Requires-Dist: pdfplumber>=0.11.0; extra == "import-tools"
Requires-Dist: Pillow>=10.0.0; extra == "import-tools"
Requires-Dist: click>=8.0.0; extra == "import-tools"
Dynamic: license-file
